rxml-2.3.6.dist-info/METADATA
rxml-2.3.6.dist-info/WHEEL
rxml-2.3.6.dist-info/licenses/LICENSE
rxml/__init__.py
rxml/__init__.pyi
rxml/py.typed
rxml/rxml.pypy310-pp73-s390x-linux-gnu.so
rxml-2.3.6.dist-info/RECORD
