Metadata-Version: 2.4
Name: rxml
Version: 2.3.6
Classifier: Programming Language :: Rust
Classifier: Programming Language :: Python :: Implementation :: CPython
Classifier: Programming Language :: Python :: Implementation :: PyPy
Classifier: Programming Language :: Python :: 3.10
Classifier: Programming Language :: Python :: 3.11
Classifier: Programming Language :: Python :: 3.12
Classifier: Programming Language :: Python :: 3.13
Classifier: Programming Language :: Python :: 3.14
Classifier: Typing :: Typed
Classifier: License :: OSI Approved :: MIT License
License-File: LICENSE
Summary: RXML is a python library to read and write xml files up to 2 times faster than python's xml included library.
Author-email: Matheus Mendes <mattheus2015@yahoo.com.br>
License-Expression: MIT
Requires-Python: >=3.10
Project-URL: Repository, https://github.com/nephi-dev/rxml
